snitcher/__init__.py
snitcher/__version.py
snitcher/snitcher.py
snitcher-0.2.2.dist-info/METADATA
snitcher-0.2.2.dist-info/RECORD
snitcher-0.2.2.dist-info/WHEEL
snitcher-0.2.2.dist-info/top_level.txt
