Metadata-Version: 2.1
Name: snitcher
Version: 0.2.2
Summary: Provides a simple listener/observer library.
Home-page: http://bitbucket.org/arcanefoam/snitcher
Author: Horacio Hoyos Rodriguez
Author-email: arcanefoam@gmail.com
License: UNKNOWN
Platform: any
Classifier: Programming Language :: Python
Classifier: Development Status :: 5 - Production/Stable
Classifier: Natural Language :: English
Classifier: Intended Audience :: Developers
Classifier: License :: OSI Approved :: Apache Software License
Classifier: Operating System :: OS Independent
Classifier: Topic :: Software Development :: Libraries :: Python Modules
